dbt/__init__.py
dbt/adapters/__init__.py
dbt/adapters/duckdb/__init__.py
dbt/adapters/duckdb/__version__.py
dbt/adapters/duckdb/column.py
dbt/adapters/duckdb/connections.py
dbt/adapters/duckdb/credentials.py
dbt/adapters/duckdb/impl.py
dbt/adapters/duckdb/relation.py
dbt/adapters/duckdb/secrets.py
dbt/adapters/duckdb/utils.py
dbt/adapters/duckdb/environments/__init__.py
dbt/adapters/duckdb/environments/buenavista.py
dbt/adapters/duckdb/environments/local.py
dbt/adapters/duckdb/plugins/__init__.py
dbt/adapters/duckdb/plugins/delta.py
dbt/adapters/duckdb/plugins/excel.py
dbt/adapters/duckdb/plugins/glue.py
dbt/adapters/duckdb/plugins/gsheet.py
dbt/adapters/duckdb/plugins/iceberg.py
dbt/adapters/duckdb/plugins/motherduck.py
dbt/adapters/duckdb/plugins/pd_utils.py
dbt/adapters/duckdb/plugins/postgres.py
dbt/adapters/duckdb/plugins/sqlalchemy.py
dbt/adapters/duckdb/plugins/unity.py
dbt/include/__init__.py
dbt/include/duckdb/__init__.py
dbt/include/duckdb/dbt_project.yml
dbt/include/duckdb/sample_profiles.yml
dbt/include/duckdb/macros/adapters.sql
dbt/include/duckdb/macros/catalog.sql
dbt/include/duckdb/macros/columns.sql
dbt/include/duckdb/macros/incremental_helper.sql
dbt/include/duckdb/macros/persist_docs.sql
dbt/include/duckdb/macros/seed.sql
dbt/include/duckdb/macros/snapshot_helper.sql
dbt/include/duckdb/macros/materializations/external.sql
dbt/include/duckdb/macros/materializations/external_table.sql
dbt/include/duckdb/macros/materializations/incremental.sql
dbt/include/duckdb/macros/materializations/ref.sql
dbt/include/duckdb/macros/materializations/table.sql
dbt/include/duckdb/macros/utils/any_value.sql
dbt/include/duckdb/macros/utils/dateadd.sql
dbt/include/duckdb/macros/utils/datediff.sql
dbt/include/duckdb/macros/utils/external_location.sql
dbt/include/duckdb/macros/utils/lastday.sql
dbt/include/duckdb/macros/utils/listagg.sql
dbt/include/duckdb/macros/utils/splitpart.sql
dbt/include/duckdb/macros/utils/upstream.sql
xd_ducklake-0.0.0.dist-info/AUTHORS
xd_ducklake-0.0.0.dist-info/LICENSE
xd_ducklake-0.0.0.dist-info/METADATA
xd_ducklake-0.0.0.dist-info/WHEEL
xd_ducklake-0.0.0.dist-info/pbr.json
xd_ducklake-0.0.0.dist-info/top_level.txt
xd_ducklake-0.0.0.dist-info/RECORD
