Metadata-Version: 2.1
Name: xd-ducklake
Version: 0.0.0
Summary: The duckdb adapter plugin for dbt (data build tool)
Home-page: https://github.com/godatadriven/dbt-duckdb
Author: Duck Lake
Author-email: duck.lake@no-reply.com
License: Apache-2
Keywords: setup,distutils
Classifier: Development Status :: 5 - Production/Stable
Classifier: License :: OSI Approved :: Apache Software License
Classifier: Operating System :: Microsoft :: Windows
Classifier: Operating System :: MacOS :: MacOS X
Classifier: Operating System :: POSIX :: Linux
Classifier: Programming Language :: Python :: 3.8
Classifier: Programming Language :: Python :: 3.9
Classifier: Programming Language :: Python :: 3.10
Classifier: Programming Language :: Python :: 3.11
Requires-Python: >=3.8
License-File: LICENSE
License-File: AUTHORS
Requires-Dist: dbt-common <2,>=1
Requires-Dist: dbt-adapters <2,>=1
Requires-Dist: duckdb ==1.0.0
Requires-Dist: tenacity >=7.0.0
Requires-Dist: dbt-core >=1.8.0
Provides-Extra: delta
Requires-Dist: deltalake ==0.18.2 ; extra == 'delta'
Requires-Dist: pyarrow ==17.0.0 ; extra == 'delta'
Provides-Extra: glue
Requires-Dist: boto3 ; extra == 'glue'
Requires-Dist: mypy-boto3-glue ; extra == 'glue'
Provides-Extra: unity
Requires-Dist: unitycatalog ==0.1.1 ; extra == 'unity'
Requires-Dist: deltalake ==0.18.2 ; extra == 'unity'
Requires-Dist: pyarrow ==17.0.0 ; extra == 'unity'
